{
  "name": "NEXUS AI System",
  "version": "2.0.0",
  "status": "ACTIVE",
  "capabilities": [
    "natural_language_processing",
    "machine_learning",
    "predictive_analytics",
    "automated_routing",
    "sentiment_analysis",
    "anomaly_detection",
    "smart_responses",
    "ticket_classification"
  ],
  "models": {
    "nlp": "enabled",
    "ml": "enabled",
    "analytics": "enabled",
    "prediction": "enabled"
  },
  "performance": {
    "accuracy": "95%+",
    "response_time": "<100ms",
    "throughput": "10,000+ requests/second"
  }
}
